{
  "label": "Temel Kavramlar ve Terimler",
  "position": 1,
  "link": {
    "type": "generated-index",
    "description": "Excel'de hücreleri biçimlendirmek, verilerin görünümünü değiştirmek, vurgulamak ve düzenlemek için kullanılan güçlü bir özelliktir. Hücreleri biçimlendirerek, verilerinizi daha okunaklı hale getirebilir, önemli bilgileri vurgulayabilir ve belirli bir tasarım veya sunum amacı için hücreleri düzenleyebilirsiniz. İşte hücreleri biçimlendirme ile ilgili önemli noktalar:    "
  }
}
