{
  "label": "Blockchain Mechanisms",
  "position": 1,
  "link": {
    "type": "generated-index",
    "description": "Blokzincir Mekanizmaları, blokzincir teknolojisinin işleyişini ve yapısını oluşturan temel bileşenleri, merkeziyetsizlikten konsensüs mekanizmalarına kadar geniş bir yelpazede ele alır. Bu kategori, güvenlik, ölçeklenebilirlik, veri bütünlüğü ve işlem doğrulama süreçlerinin yanı sıra kripto madenciliği ve düğüm yapılarını da içeren çeşitli konseptlerin derinlemesine incelenmesini sağlar."
  }
}