{
  "label": "Zincirler Arası Entegrasyon",
  "position": 1,
  "link": {
    "type": "generated-index",
    "description": "Çapraz zincir entegrasyonu kategorisi, BNB Greenfield platformu ile BSC ve opBNB ağları arasında veri modellemesi ve akıllı sözleşme yönetimi süreçlerini optimize etmeyi amaçlayan belgeleri içerir. Geliştiricilere, EVM uyumlu kaynakların yönetimi ve çapraz zincir işlemlerinin entegrasyonu hakkında kapsamlı bilgiler sunarak, güvenli ve verimli uygulama geliştirme imkanı sağlar."
  }
}